{
      "resourceType" : "MedicationRequest",
      "id" : "acb4d2b8-79cb-440b-afb1-5a875eaddb24",
      "meta" : {
        "profile" : ["https://interop.aphp.fr/ig/fhir/dm/StructureDefinition/DMMedicationRequest"]
      },
      "status" : "active",
      "intent" : "order",
      "medicationCodeableConcept" : {
        "coding" : [{
          "code" : "37533",
          "display" : "Ticagrelor 90mg"
        }]
      },
      "subject" : {
        "reference" : "Patient/73ed8b6d-e761-4f71-b69d-475a1be9f487"
      },
      "dosageInstruction" : [{
        "timing" : {
          "repeat" : {
            "boundsPeriod" : {
              "start" : "2024-01-11",
              "end" : "2025-01-12"
            }
          }
        },
        "route" : {
          "coding" : [{
            "code" : "20053000"
          }]
        }
      }]
    }